dnet/__init__.py
dnet/manager_factory.py
dnet/Api/__init__.py
dnet/Api/api_manager.py
dnet/Api/graphql_queries.py
dnet/Coin/__init__.py
dnet/Coin/coin_manager.py
dnet/Coin/graphql_queries.py
dnet/Explorer/__init__.py
dnet/Explorer/explorer_manager.py
dnet/Explorer/graphql_queries.py
dnet/Transaction/__init__.py
dnet/Transaction/graphql_queries.py
dnet/Transaction/transaction_manager.py
dnet/User/graphql_queries.py
dnet/User/user_manager.py
dnet/Wallet/__init__.py
dnet/Wallet/graphql_queries.py
dnet/Wallet/wallet_manager.py
dnet/tests/__init__.py
dnet/tests/test_api_manager.py
dnet/tests/test_wallet_manager.py
dnetwork-0.2.1.0.33.dist-info/METADATA
dnetwork-0.2.1.0.33.dist-info/WHEEL
dnetwork-0.2.1.0.33.dist-info/top_level.txt
dnetwork-0.2.1.0.33.dist-info/RECORD
