Metadata-Version: 2.4
Name: dnetwork
Version: 0.2.1.0.33
Summary: My project demo
Author-email: Dnetwork-Team <webdev2123@gmail.com>
License: MIT License
Keywords: one,two
Classifier: Framework :: Django
Classifier: Programming Language :: Python :: 3
Requires-Python: >=3.8
Requires-Dist: gql[all]==3.5.2
Requires-Dist: websockets
Requires-Dist: requests-toolbelt
Requires-Dist: pytest
Requires-Dist: pytest-mock
Requires-Dist: pytest-cov
Requires-Dist: importlib-metadata; python_version > "3.7"
Provides-Extra: dev
Requires-Dist: pytest; extra == "dev"
Requires-Dist: pytest-mock; extra == "dev"
Requires-Dist: pytest-cov; extra == "dev"
Requires-Dist: black; extra == "dev"
Requires-Dist: mypy; extra == "dev"
Requires-Dist: ruff; extra == "dev"
Requires-Dist: gql[all]; extra == "dev"
Provides-Extra: test
Requires-Dist: pytest; extra == "test"
Requires-Dist: pytest-mock; extra == "test"
Requires-Dist: pytest-cov; extra == "test"
Provides-Extra: build
Requires-Dist: build; extra == "build"
